MicroLIA/__init__.py
MicroLIA/cnn_model.py
MicroLIA/ensemble_model.py
MicroLIA/extract_features.py
MicroLIA/feature_selection.py
MicroLIA/features.py
MicroLIA/helper_features.py
MicroLIA/noise_models.py
MicroLIA/optimization.py
MicroLIA/quality_check.py
MicroLIA/simulate.py
MicroLIA/training_set.py
MicroLIA/data/Miras_vo.xml
MicroLIA/data/__init__.py
MicroLIA/data/Sesar2010/RRLyr_ugriz_templates.tar.gz
MicroLIA/data/Sesar2010/__init__.py
MicroLIA/test/MicroLIA_Training_Set_OGLE_IV.csv
MicroLIA/test/__init__.py
MicroLIA/test/test_classifier.py
MicroLIA/test/test_features.py
MicroLIA/test/test_ogle_lc.dat
MicroLIA/test/test_model_xgb/MicroLIA_ensemble_model/Best_Params
MicroLIA/test/test_model_xgb/MicroLIA_ensemble_model/Feats_Index
MicroLIA/test/test_model_xgb/MicroLIA_ensemble_model/FeatureOpt_Results
MicroLIA/test/test_model_xgb/MicroLIA_ensemble_model/HyperOpt_Results
MicroLIA/test/test_model_xgb/MicroLIA_ensemble_model/Imputer
MicroLIA/test/test_model_xgb/MicroLIA_ensemble_model/Model
microlia-2.8.1.dist-info/licenses/LICENSE.txt
microlia-2.8.1.dist-info/METADATA
microlia-2.8.1.dist-info/WHEEL
microlia-2.8.1.dist-info/top_level.txt
microlia-2.8.1.dist-info/RECORD
